prettify_py/__init__.py
prettify_py/formatter.py
prettify_py/split_line_cutoff.py
prettify_py-0.2.3.12.dist-info/METADATA
prettify_py-0.2.3.12.dist-info/WHEEL
prettify_py-0.2.3.12.dist-info/entry_points.txt
prettify_py-0.2.3.12.dist-info/top_level.txt
prettify_py-0.2.3.12.dist-info/RECORD
