Metadata-Version: 2.1
Name: prettify-py
Version: 0.2.3.12
Summary: CLI for prettifying Python
Home-page: http://www.codeberg/cap_jmk/prettify-py
Author: Julian M. Kleber
Author-email: julian.kleber@sail.black
Classifier: Programming Language :: Python :: 3
Classifier: License :: OSI Approved :: GNU General Public License v3 (GPLv3)
Classifier: Operating System :: OS Independent
Requires-Python: >=3.8
Requires-Dist: Click
Requires-Dist: docformatter
Requires-Dist: black
Requires-Dist: amarium
